<?xml version='1.0' encoding='utf8'?>
<DOC article="0004" id="HYT_ARB_199401030004" newspaper="HYT_ARB_19940103">
		<headline>فوز لظافر حامل اللقب . الهزيمة الأولى للبستان في الدوري العماني للكرة</headline>
		<dateline>سالم الحبسي</dateline>
		<text>
			<p>تعرض فريق البستان لخسارته الأولى في الدوري العماني لكرة القدم عندما فاز عليه فريق الشرطة بهدف يتيم أحرزه المهاجم السنغالي حسام أنجاي في الدقيقة ال 11 من المباراة التي أجريت أول من أمس في قمة الأسبوع التاسع .</p>
			<p>وبقي البستان رغم خسارته متصدرا ترتيب الدوري للأسبوع الثاني على التوالي على حساب الشرطة الذي كان احتل القمة ثلاثة أسابيع , وتساوى الفريقان في الرصيد ولكل منهما 11 نقطة , ويتقدم البستان بفارق الأهداف .</p>
			<p>وكان هدف الشرطة جاء مبكرا , سعى البستان الى تعديل النتيجة , الا ان كل المحاولات باءت بالفشل , بما فيها ركلة الجزاء التي احتسبت للفريق في الدقيقة ال 20 وأهدرها الطيب عبدالنور .</p>
			<p>وحقق ظفار حامل اللقب فوزا مهما على غريمه مرباط بهدف لشريف سنجور في مباراة أقيمت أمام مدرجات خالية تنفيذا لعقوبة فرضها اتحاد اللعبة على ظفار بعد احداث الشغب التي أثارها جمهوره في بداية الموسم .</p>
			<p>واستمر التساوي بين الخابورة وعمان بعد تعادلها السلبي وتقاسمها نقطتي المباراة وارتفع رصيد كل منهما الى 8 نقاط .</p>
			<p>وفجر السيب المتقوقع في قاع الدوري مفاجأة الأسبوع عندما هزم العروبة بطل الكأس ( 2 / 1 ) محققا فوزه الثاني هذا الموسم . وبه خرج من القاع ورفع رصيده الى 8 نقاط , فيما توقف رصيد العروبة عند 9 نقاط .</p>
			<p>وتقدم الفائز بهدفين أحرزهما عبدالحميد عبدالله من ضربة رأسية ويونس الفهدي , اما هدف العروبة فأحرزه سعيد ناصر الفارسي في الدقيقة الأخيرة من المباراة .</p>
			<p>وفاز النصر على سداب بهدف أحرزه مروان رجب في الدقيقة ال 83 , فيما دخل صور بطل الكأس في الموسم الماضي في مأزق وتعرض لخسارة غير متوقعة امام الهلال بهدف أحرزه أحمد سعيد .</p>
		</text>
	</DOC>

	