<?xml version='1.0' encoding='utf8'?>
<DOC article="0065" id="HYT_ARB_199401070065" newspaper="HYT_ARB_19940107">
		<headline>رئيس مجلس النواب الأردني يزور سورية</headline>
		<text>
			<p>بحث وزير الخارجية السوري السيد فاروق الشرع أمس مع السيد طاهر المصري رئيس مجلس النواب الأردني في تطورات عملية السلام في الشرق الأوسط والتنسيق العربي .</p>
			<p>وقال مسؤولون ان الحديث تناول أيضا أهمية اجتماع القمة بين الرئيسين حافظ الأسد وبيل كلينتون في جنيف في 16 كانون الثاني ( يناير ) الجاري في العمل لتحقيق السلام العادل والشامل في المنطقة .</p>
			<p>وكان المصري وصل الى دمشق أمس واجتمع مع نائب الرئيس السوري وجرى أيضا الحديث حول عملية السلام التي تشترك فيها سورية والأردن بالاضافة للبحث في بعض الأمور الثنائية .</p>
			<p>كما اجتمع المصري فور وصوله مع رئيس مجلس الشعب السوري السيد عبدالقادر قدوره وتم البحث في العلاقات البرلمانية بين سورية والأردن والقضايا المتعلقة بالاتحاد البرلماني العربي ونشاطاته .</p>
			<p>وأعرب المصري في تصريح لدى وصوله الى سورية عن تطلعه لاجراء لقاءات " مثمرة ومفيدة " مع المسؤولين السوريين .</p>
			<p>وقال " هذه الزيارة بداية لزيارات متبادلة بين المجلسين في البلدين الشقيقين وهناك بعض القضايا العامة التي تتعلق باتحاد البرلمانات العربية " .</p>
			<p>وأضاف " ان أهمية الزيارة تأتي في الدرجة الأولى من تأكيد التفاعل والاتصال بين الأردن وسورية وبين المجلسين في البلدين الشقيقين " .</p>
		</text>
	</DOC>
	
