<?xml version='1.0' encoding='utf8'?>
<DOC article="0025" id="HYT_ARB_199401090025" newspaper="HYT_ARB_19940109">
		<headline>ابن كارلوس منعم متهم بالاعتداء على مصور في الاوروغواي</headline>
		<text>
			<p>بثت محطة تلفزيون في الأوروغواي أول من امس ان الشرطة تستجوب ابن الرئيس الارجنتيني كارلوس منعم بعدما تعرض مصور احدى المجلات للضرب في المنتجع السياحي الراقي بونتا دل استي .</p>
			<p>وبثت الاذاعة لاحقا ان القاضي داكوتا بورتو استدعى كارلوس منعم الابن ( 24 عاما ) واثنين من حراسه للاستجواب بعدما تلقت الشرطة بلاغا من هنري فون واتمبرغ المصور الصحافي في المجلة الارجنتينية " جنت " عن تعرضه للضرب في ملهى ليل الخميس الماضي .</p>
			<p>ونقلت الاذاعة عن المصور قوله " كنت احاول ان التقط صورا لعارضات ازياء حين فوجئت بكارلوس منعم الابن يسير نحوي ويهددني بالضرب " . وتابع " على الرغم من انني اوضحت له عدم رغبتي في التقاط اي صور له , فقد اقدم مع عدد من حراسه على ضربي بوحشية " .</p>
			<p>يذكر ان بونتا دل استي من الاماكن السياحية المفضلة لدى الارجنتينيين الاثرياء .</p>
		</text>
	</DOC>
	
